AUTHORS
COPYING
ChangeLog
MANIFEST.in
README.rst
setup.py
data/pysysbot.conf
data/pysysbot.service
man/pysysbot.1
pysysbot/__init__.py
pysysbot/constants.py
pysysbot/pysysbot.py
pysysbot/replies.py
pysysbot/settings.py
pysysbot.egg-info/PKG-INFO
pysysbot.egg-info/SOURCES.txt
pysysbot.egg-info/dependency_links.txt
pysysbot.egg-info/entry_points.txt
pysysbot.egg-info/requires.txt
pysysbot.egg-info/top_level.txt