Metadata-Version: 1.2
Name: pysysbot
Version: 0.3.0
Summary: Python based system jabber bot
Home-page: http://affolter-engineering.ch/pysysbot/
Author: Fabian Affolter
Author-email: fabian@affolter-engineering.ch
Maintainer: Fabian Affolter
Maintainer-email: fabian@affolter-engineering.ch
License: BSD
Keywords: Jabber,XMPP,System,python
Platform: Linux
Classifier: Development Status :: 4 - Beta
Classifier: Environment :: Console
Classifier: Intended Audience :: End Users/Desktop
Classifier: Intended Audience :: System Administrators
Classifier: License :: OSI Approved :: BSD License
Classifier: Operating System :: POSIX
Classifier: Programming Language :: Python
Classifier: Topic :: Communications
Classifier: Topic :: Internet
Classifier: Topic :: System
Classifier: Topic :: System :: Monitoring
